<?xml version="1.0" encoding="UTF-8" standalone="yes"?>
<w:webSettings xmlns:r="http://schemas.openxmlformats.org/officeDocument/2006/relationships" xmlns:w="http://schemas.openxmlformats.org/wordprocessingml/2006/main"><w:divs><w:div w:id="110591868"><w:bodyDiv w:val="1"/><w:marLeft w:val="0"/><w:marRight w:val="0"/><w:marTop w:val="0"/><w:marBottom w:val="0"/><w:divBdr><w:top w:val="none" w:sz="0" w:space="0" w:color="auto"/><w:left w:val="none" w:sz="0" w:space="0" w:color="auto"/><w:bottom w:val="none" w:sz="0" w:space="0" w:color="auto"/><w:right w:val="none" w:sz="0" w:space="0" w:color="auto"/></w:divBdr></w:div><w:div w:id="203059727"><w:bodyDiv w:val="1"/><w:marLeft w:val="0"/><w:marRight w:val="0"/><w:marTop w:val="0"/><w:marBottom w:val="0"/><w:divBdr><w:top w:val="none" w:sz="0" w:space="0" w:color="auto"/><w:left w:val="none" w:sz="0" w:space="0" w:color="auto"/><w:bottom w:val="none" w:sz="0" w:space="0" w:color="auto"/><w:right w:val="none" w:sz="0" w:space="0" w:color="auto"/></w:divBdr></w:div><w:div w:id="639312647"><w:bodyDiv w:val="1"/><w:marLeft w:val="0"/><w:marRight w:val="0"/><w:marTop w:val="0"/><w:marBottom w:val="0"/><w:divBdr><w:top w:val="none" w:sz="0" w:space="0" w:color="auto"/><w:left w:val="none" w:sz="0" w:space="0" w:color="auto"/><w:bottom w:val="none" w:sz="0" w:space="0" w:color="auto"/><w:right w:val="none" w:sz="0" w:space="0" w:color="auto"/></w:divBdr></w:div><w:div w:id="754591090"><w:bodyDiv w:val="1"/><w:marLeft w:val="0"/><w:marRight w:val="0"/><w:marTop w:val="0"/><w:marBottom w:val="0"/><w:divBdr><w:top w:val="none" w:sz="0" w:space="0" w:color="auto"/><w:left w:val="none" w:sz="0" w:space="0" w:color="auto"/><w:bottom w:val="none" w:sz="0" w:space="0" w:color="auto"/><w:right w:val="none" w:sz="0" w:space="0" w:color="auto"/></w:divBdr><w:divsChild><w:div w:id="687489403"><w:marLeft w:val="0"/><w:marRight w:val="0"/><w:marTop w:val="0"/><w:marBottom w:val="0"/><w:divBdr><w:top w:val="none" w:sz="0" w:space="0" w:color="auto"/><w:left w:val="none" w:sz="0" w:space="0" w:color="auto"/><w:bottom w:val="none" w:sz="0" w:space="0" w:color="auto"/><w:right w:val="none" w:sz="0" w:space="0" w:color="auto"/></w:divBdr><w:divsChild><w:div w:id="1724332988"><w:marLeft w:val="0"/><w:marRight w:val="0"/><w:marTop w:val="0"/><w:marBottom w:val="0"/><w:divBdr><w:top w:val="none" w:sz="0" w:space="0" w:color="auto"/><w:left w:val="none" w:sz="0" w:space="0" w:color="auto"/><w:bottom w:val="none" w:sz="0" w:space="0" w:color="auto"/><w:right w:val="none" w:sz="0" w:space="0" w:color="auto"/></w:divBdr><w:divsChild><w:div w:id="1870608164"><w:marLeft w:val="0"/><w:marRight w:val="0"/><w:marTop w:val="0"/><w:marBottom w:val="0"/><w:divBdr><w:top w:val="none" w:sz="0" w:space="0" w:color="auto"/><w:left w:val="none" w:sz="0" w:space="0" w:color="auto"/><w:bottom w:val="none" w:sz="0" w:space="0" w:color="auto"/><w:right w:val="none" w:sz="0" w:space="0" w:color="auto"/></w:divBdr><w:divsChild><w:div w:id="333461631"><w:marLeft w:val="0"/><w:marRight w:val="0"/><w:marTop w:val="0"/><w:marBottom w:val="0"/><w:divBdr><w:top w:val="none" w:sz="0" w:space="0" w:color="auto"/><w:left w:val="none" w:sz="0" w:space="0" w:color="auto"/><w:bottom w:val="none" w:sz="0" w:space="0" w:color="auto"/><w:right w:val="none" w:sz="0" w:space="0" w:color="auto"/></w:divBdr><w:divsChild><w:div w:id="38285339"><w:marLeft w:val="0"/><w:marRight w:val="0"/><w:marTop w:val="0"/><w:marBottom w:val="0"/><w:divBdr><w:top w:val="none" w:sz="0" w:space="0" w:color="auto"/><w:left w:val="none" w:sz="0" w:space="0" w:color="auto"/><w:bottom w:val="none" w:sz="0" w:space="0" w:color="auto"/><w:right w:val="none" w:sz="0" w:space="0" w:color="auto"/></w:divBdr><w:divsChild><w:div w:id="1715230002"><w:marLeft w:val="0"/><w:marRight w:val="0"/><w:marTop w:val="0"/><w:marBottom w:val="0"/><w:divBdr><w:top w:val="none" w:sz="0" w:space="0" w:color="auto"/><w:left w:val="none" w:sz="0" w:space="0" w:color="auto"/><w:bottom w:val="single" w:sz="18" w:space="0" w:color="E4E4E4"/><w:right w:val="none" w:sz="0" w:space="0" w:color="auto"/></w:divBdr><w:divsChild><w:div w:id="2027054123"><w:marLeft w:val="0"/><w:marRight w:val="0"/><w:marTop w:val="0"/><w:marBottom w:val="0"/><w:divBdr><w:top w:val="none" w:sz="0" w:space="0" w:color="auto"/><w:left w:val="none" w:sz="0" w:space="0" w:color="auto"/><w:bottom w:val="none" w:sz="0" w:space="0" w:color="auto"/><w:right w:val="none" w:sz="0" w:space="0" w:color="auto"/></w:divBdr><w:divsChild><w:div w:id="1992365544"><w:marLeft w:val="0"/><w:marRight w:val="0"/><w:marTop w:val="0"/><w:marBottom w:val="0"/><w:divBdr><w:top w:val="none" w:sz="0" w:space="0" w:color="auto"/><w:left w:val="none" w:sz="0" w:space="0" w:color="auto"/><w:bottom w:val="none" w:sz="0" w:space="0" w:color="auto"/><w:right w:val="none" w:sz="0" w:space="0" w:color="auto"/></w:divBdr><w:divsChild><w:div w:id="1038503754"><w:marLeft w:val="0"/><w:marRight w:val="0"/><w:marTop w:val="0"/><w:marBottom w:val="0"/><w:divBdr><w:top w:val="none" w:sz="0" w:space="0" w:color="auto"/><w:left w:val="none" w:sz="0" w:space="0" w:color="auto"/><w:bottom w:val="none" w:sz="0" w:space="0" w:color="auto"/><w:right w:val="none" w:sz="0" w:space="0" w:color="auto"/></w:divBdr><w:divsChild><w:div w:id="599488242"><w:marLeft w:val="0"/><w:marRight w:val="0"/><w:marTop w:val="0"/><w:marBottom w:val="0"/><w:divBdr><w:top w:val="none" w:sz="0" w:space="0" w:color="auto"/><w:left w:val="none" w:sz="0" w:space="0" w:color="auto"/><w:bottom w:val="none" w:sz="0" w:space="0" w:color="auto"/><w:right w:val="none" w:sz="0" w:space="0" w:color="auto"/></w:divBdr><w:divsChild><w:div w:id="184483917"><w:marLeft w:val="0"/><w:marRight w:val="0"/><w:marTop w:val="0"/><w:marBottom w:val="0"/><w:divBdr><w:top w:val="none" w:sz="0" w:space="0" w:color="auto"/><w:left w:val="none" w:sz="0" w:space="0" w:color="auto"/><w:bottom w:val="none" w:sz="0" w:space="0" w:color="auto"/><w:right w:val="none" w:sz="0" w:space="0" w:color="auto"/></w:divBdr></w:div><w:div w:id="656106924"><w:marLeft w:val="0"/><w:marRight w:val="0"/><w:marTop w:val="0"/><w:marBottom w:val="0"/><w:divBdr><w:top w:val="none" w:sz="0" w:space="0" w:color="auto"/><w:left w:val="none" w:sz="0" w:space="0" w:color="auto"/><w:bottom w:val="none" w:sz="0" w:space="0" w:color="auto"/><w:right w:val="none" w:sz="0" w:space="0" w:color="auto"/></w:divBdr></w:div></w:divsChild></w:div></w:divsChild></w:div></w:divsChild></w:div></w:divsChild></w:div></w:divsChild></w:div></w:divsChild></w:div></w:divsChild></w:div></w:divsChild></w:div></w:divsChild></w:div></w:divsChild></w:div></w:divsChild></w:div><w:div w:id="1042485211"><w:bodyDiv w:val="1"/><w:marLeft w:val="0"/><w:marRight w:val="0"/><w:marTop w:val="0"/><w:marBottom w:val="0"/><w:divBdr><w:top w:val="none" w:sz="0" w:space="0" w:color="auto"/><w:left w:val="none" w:sz="0" w:space="0" w:color="auto"/><w:bottom w:val="none" w:sz="0" w:space="0" w:color="auto"/><w:right w:val="none" w:sz="0" w:space="0" w:color="auto"/></w:divBdr></w:div><w:div w:id="1601987507"><w:bodyDiv w:val="1"/><w:marLeft w:val="0"/><w:marRight w:val="0"/><w:marTop w:val="0"/><w:marBottom w:val="0"/><w:divBdr><w:top w:val="none" w:sz="0" w:space="0" w:color="auto"/><w:left w:val="none" w:sz="0" w:space="0" w:color="auto"/><w:bottom w:val="none" w:sz="0" w:space="0" w:color="auto"/><w:right w:val="none" w:sz="0" w:space="0" w:color="auto"/></w:divBdr></w:div><w:div w:id="1828092072"><w:bodyDiv w:val="1"/><w:marLeft w:val="0"/><w:marRight w:val="0"/><w:marTop w:val="0"/><w:marBottom w:val="0"/><w:divBdr><w:top w:val="none" w:sz="0" w:space="0" w:color="auto"/><w:left w:val="none" w:sz="0" w:space="0" w:color="auto"/><w:bottom w:val="none" w:sz="0" w:space="0" w:color="auto"/><w:right w:val="none" w:sz="0" w:space="0" w:color="auto"/></w:divBdr><w:divsChild><w:div w:id="39325640"><w:marLeft w:val="0"/><w:marRight w:val="0"/><w:marTop w:val="0"/><w:marBottom w:val="0"/><w:divBdr><w:top w:val="none" w:sz="0" w:space="0" w:color="auto"/><w:left w:val="none" w:sz="0" w:space="0" w:color="auto"/><w:bottom w:val="none" w:sz="0" w:space="0" w:color="auto"/><w:right w:val="none" w:sz="0" w:space="0" w:color="auto"/></w:divBdr><w:divsChild><w:div w:id="1860123228"><w:marLeft w:val="0"/><w:marRight w:val="0"/><w:marTop w:val="0"/><w:marBottom w:val="0"/><w:divBdr><w:top w:val="none" w:sz="0" w:space="0" w:color="auto"/><w:left w:val="none" w:sz="0" w:space="0" w:color="auto"/><w:bottom w:val="none" w:sz="0" w:space="0" w:color="auto"/><w:right w:val="none" w:sz="0" w:space="0" w:color="auto"/></w:divBdr><w:divsChild><w:div w:id="704722453"><w:marLeft w:val="0"/><w:marRight w:val="0"/><w:marTop w:val="0"/><w:marBottom w:val="0"/><w:divBdr><w:top w:val="none" w:sz="0" w:space="0" w:color="auto"/><w:left w:val="none" w:sz="0" w:space="0" w:color="auto"/><w:bottom w:val="none" w:sz="0" w:space="0" w:color="auto"/><w:right w:val="none" w:sz="0" w:space="0" w:color="auto"/></w:divBdr><w:divsChild><w:div w:id="2020304744"><w:marLeft w:val="0"/><w:marRight w:val="0"/><w:marTop w:val="0"/><w:marBottom w:val="0"/><w:divBdr><w:top w:val="none" w:sz="0" w:space="0" w:color="auto"/><w:left w:val="none" w:sz="0" w:space="0" w:color="auto"/><w:bottom w:val="none" w:sz="0" w:space="0" w:color="auto"/><w:right w:val="none" w:sz="0" w:space="0" w:color="auto"/></w:divBdr><w:divsChild><w:div w:id="1958759973"><w:marLeft w:val="0"/><w:marRight w:val="0"/><w:marTop w:val="0"/><w:marBottom w:val="0"/><w:divBdr><w:top w:val="none" w:sz="0" w:space="0" w:color="auto"/><w:left w:val="none" w:sz="0" w:space="0" w:color="auto"/><w:bottom w:val="none" w:sz="0" w:space="0" w:color="auto"/><w:right w:val="none" w:sz="0" w:space="0" w:color="auto"/></w:divBdr><w:divsChild><w:div w:id="1863977808"><w:marLeft w:val="0"/><w:marRight w:val="0"/><w:marTop w:val="0"/><w:marBottom w:val="0"/><w:divBdr><w:top w:val="none" w:sz="0" w:space="0" w:color="auto"/><w:left w:val="none" w:sz="0" w:space="0" w:color="auto"/><w:bottom w:val="single" w:sz="18" w:space="0" w:color="E4E4E4"/><w:right w:val="none" w:sz="0" w:space="0" w:color="auto"/></w:divBdr><w:divsChild><w:div w:id="503014890"><w:marLeft w:val="0"/><w:marRight w:val="0"/><w:marTop w:val="0"/><w:marBottom w:val="0"/><w:divBdr><w:top w:val="none" w:sz="0" w:space="0" w:color="auto"/><w:left w:val="none" w:sz="0" w:space="0" w:color="auto"/><w:bottom w:val="none" w:sz="0" w:space="0" w:color="auto"/><w:right w:val="none" w:sz="0" w:space="0" w:color="auto"/></w:divBdr><w:divsChild><w:div w:id="308024582"><w:marLeft w:val="0"/><w:marRight w:val="0"/><w:marTop w:val="0"/><w:marBottom w:val="0"/><w:divBdr><w:top w:val="none" w:sz="0" w:space="0" w:color="auto"/><w:left w:val="none" w:sz="0" w:space="0" w:color="auto"/><w:bottom w:val="none" w:sz="0" w:space="0" w:color="auto"/><w:right w:val="none" w:sz="0" w:space="0" w:color="auto"/></w:divBdr><w:divsChild><w:div w:id="1969779941"><w:marLeft w:val="0"/><w:marRight w:val="0"/><w:marTop w:val="0"/><w:marBottom w:val="0"/><w:divBdr><w:top w:val="none" w:sz="0" w:space="0" w:color="auto"/><w:left w:val="none" w:sz="0" w:space="0" w:color="auto"/><w:bottom w:val="none" w:sz="0" w:space="0" w:color="auto"/><w:right w:val="none" w:sz="0" w:space="0" w:color="auto"/></w:divBdr><w:divsChild><w:div w:id="1170097553"><w:marLeft w:val="0"/><w:marRight w:val="0"/><w:marTop w:val="0"/><w:marBottom w:val="0"/><w:divBdr><w:top w:val="none" w:sz="0" w:space="0" w:color="auto"/><w:left w:val="none" w:sz="0" w:space="0" w:color="auto"/><w:bottom w:val="none" w:sz="0" w:space="0" w:color="auto"/><w:right w:val="none" w:sz="0" w:space="0" w:color="auto"/></w:divBdr><w:divsChild><w:div w:id="619142701"><w:marLeft w:val="0"/><w:marRight w:val="0"/><w:marTop w:val="0"/><w:marBottom w:val="0"/><w:divBdr><w:top w:val="none" w:sz="0" w:space="0" w:color="auto"/><w:left w:val="none" w:sz="0" w:space="0" w:color="auto"/><w:bottom w:val="none" w:sz="0" w:space="0" w:color="auto"/><w:right w:val="none" w:sz="0" w:space="0" w:color="auto"/></w:divBdr></w:div><w:div w:id="1974560517"><w:marLeft w:val="0"/><w:marRight w:val="0"/><w:marTop w:val="0"/><w:marBottom w:val="0"/><w:divBdr><w:top w:val="none" w:sz="0" w:space="0" w:color="auto"/><w:left w:val="none" w:sz="0" w:space="0" w:color="auto"/><w:bottom w:val="none" w:sz="0" w:space="0" w:color="auto"/><w:right w:val="none" w:sz="0" w:space="0" w:color="auto"/></w:divBdr></w:div></w:divsChild></w:div></w:divsChild></w:div></w:divsChild></w:div></w:divsChild></w:div></w:divsChild></w:div></w:divsChild></w:div></w:divsChild></w:div></w:divsChild></w:div></w:divsChild></w:div></w:divsChild></w:div></w:divsChild></w:div></w:divs><w:relyOnVML/><w:allowPNG/></w:webSettings>